README.md
setup.py
didi_eda.egg-info/PKG-INFO
didi_eda.egg-info/SOURCES.txt
didi_eda.egg-info/dependency_links.txt
didi_eda.egg-info/top_level.txt
eda/__init__.py
eda/eda.py